gatv2_eqx/__init__.py
gatv2_eqx/model.py
gatv2_eqx-0.1.1.dist-info/METADATA
gatv2_eqx-0.1.1.dist-info/WHEEL
gatv2_eqx-0.1.1.dist-info/RECORD
