Metadata-Version: 2.3
Name: gatv2_eqx
Version: 0.1.1
Summary: Add your description here
Author-email: Marcell Vazquez-Chanlatte <mvc@linux.com>
Requires-Python: >=3.8
Requires-Dist: beartype>=0.19.0
Requires-Dist: einops>=0.8.0
Requires-Dist: equinox>=0.11.8
Requires-Dist: jax[cuda12]>=0.4.34
Requires-Dist: jaxtyping>=0.2.34
